dpmModule/__init__.py
dpmModule/boss/__init__.py
dpmModule/boss/kernel.py
dpmModule/character/__init__.py
dpmModule/character/characterKernel.py
dpmModule/character/characterTemplate.py
dpmModule/character/characterTemplateHigh.py
dpmModule/character/characterTemplateLow.py
dpmModule/execution/__init__.py
dpmModule/execution/rules.py
dpmModule/item/Absolab.py
dpmModule/item/Arcane.py
dpmModule/item/BossAccesory.py
dpmModule/item/Darkness.py
dpmModule/item/Default.py
dpmModule/item/Else.py
dpmModule/item/Empress.py
dpmModule/item/ItemKernel.py
dpmModule/item/ItemTemplate.py
dpmModule/item/Meister.py
dpmModule/item/RootAbyss.py
dpmModule/item/Tyrant.py
dpmModule/item/__init__.py
dpmModule/jobs/__init__.py
dpmModule/jobs/angelicbuster.py
dpmModule/jobs/aran.py
dpmModule/jobs/archmageFb.py
dpmModule/jobs/archmageTc.py
dpmModule/jobs/ark.py
dpmModule/jobs/battlemage.py
dpmModule/jobs/bishop.py
dpmModule/jobs/blaster.py
dpmModule/jobs/bowmaster.py
dpmModule/jobs/cadena.py
dpmModule/jobs/cannonshooter.py
dpmModule/jobs/captain.py
dpmModule/jobs/contrib.py
dpmModule/jobs/darknight.py
dpmModule/jobs/demonavenger.py
dpmModule/jobs/demonslayer.py
dpmModule/jobs/dualblade.py
dpmModule/jobs/eunwol.py
dpmModule/jobs/evan.py
dpmModule/jobs/flamewizard.py
dpmModule/jobs/globalSkill.py
dpmModule/jobs/hero.py
dpmModule/jobs/hoyoung.py
dpmModule/jobs/ilium.py
dpmModule/jobs/kaiser.py
dpmModule/jobs/kinesis.py
dpmModule/jobs/luminous.py
dpmModule/jobs/mechanic.py
dpmModule/jobs/mercedes.py
dpmModule/jobs/michael.py
dpmModule/jobs/nightlord.py
dpmModule/jobs/nightwalker.py
dpmModule/jobs/paladin.py
dpmModule/jobs/pathfinder.py
dpmModule/jobs/phantom.py
dpmModule/jobs/shadower.py
dpmModule/jobs/sniper.py
dpmModule/jobs/soulmaster.py
dpmModule/jobs/store.py
dpmModule/jobs/striker.py
dpmModule/jobs/viper.py
dpmModule/jobs/wildhunter.py
dpmModule/jobs/windBreaker.py
dpmModule/jobs/zenon.py
dpmModule/jobs/zero.py
dpmModule/jobs/jobbranch/__init__.py
dpmModule/jobs/jobbranch/bowmen.py
DpmModule-1.1.0.dist-info/METADATA
DpmModule-1.1.0.dist-info/WHEEL
DpmModule-1.1.0.dist-info/top_level.txt
DpmModule-1.1.0.dist-info/RECORD
