Metadata-Version: 2.1
Name: DpmModule
Version: 1.1.0
Summary: Python module for Maplestory calculation / simulation
Home-page: https://github.com/oleneyl/maplestory_dpm_calc
Author: oleneyl
Author-email: meson3241@gmail.com
License: UNKNOWN
Keywords: game,maplestory,simulation
Platform: UNKNOWN
Classifier: Programming Language :: Python :: 3
Classifier: Programming Language :: Python :: 3.2
Classifier: Programming Language :: Python :: 3.3
Classifier: Programming Language :: Python :: 3.4
Classifier: Programming Language :: Python :: 3.5
Classifier: Programming Language :: Python :: 3.6
Classifier: Programming Language :: Python :: 3.7
Requires-Python: >=3
